euroeval/__init__.py
euroeval/benchmark_config_factory.py
euroeval/benchmarker.py
euroeval/caching_utils.py
euroeval/callbacks.py
euroeval/cli.py
euroeval/constants.py
euroeval/data_loading.py
euroeval/data_models.py
euroeval/enums.py
euroeval/exceptions.py
euroeval/finetuning.py
euroeval/generation.py
euroeval/generation_utils.py
euroeval/languages.py
euroeval/logging_utils.py
euroeval/model_cache.py
euroeval/model_config.py
euroeval/model_loading.py
euroeval/scores.py
euroeval/speed_benchmark.py
euroeval/tasks.py
euroeval/tokenisation_utils.py
euroeval/types.py
euroeval/utils.py
euroeval/benchmark_modules/__init__.py
euroeval/benchmark_modules/base.py
euroeval/benchmark_modules/fresh.py
euroeval/benchmark_modules/hf.py
euroeval/benchmark_modules/litellm.py
euroeval/benchmark_modules/vllm.py
euroeval/dataset_configs/__init__.py
euroeval/dataset_configs/albanian.py
euroeval/dataset_configs/bosnian.py
euroeval/dataset_configs/bulgarian.py
euroeval/dataset_configs/catalan.py
euroeval/dataset_configs/croatian.py
euroeval/dataset_configs/czech.py
euroeval/dataset_configs/danish.py
euroeval/dataset_configs/dutch.py
euroeval/dataset_configs/english.py
euroeval/dataset_configs/estonian.py
euroeval/dataset_configs/faroese.py
euroeval/dataset_configs/finnish.py
euroeval/dataset_configs/french.py
euroeval/dataset_configs/german.py
euroeval/dataset_configs/greek.py
euroeval/dataset_configs/hungarian.py
euroeval/dataset_configs/icelandic.py
euroeval/dataset_configs/italian.py
euroeval/dataset_configs/latvian.py
euroeval/dataset_configs/lithuanian.py
euroeval/dataset_configs/norwegian.py
euroeval/dataset_configs/polish.py
euroeval/dataset_configs/portuguese.py
euroeval/dataset_configs/romanian.py
euroeval/dataset_configs/serbian.py
euroeval/dataset_configs/slovak.py
euroeval/dataset_configs/slovene.py
euroeval/dataset_configs/spanish.py
euroeval/dataset_configs/swedish.py
euroeval/dataset_configs/ukrainian.py
euroeval/metrics/__init__.py
euroeval/metrics/base.py
euroeval-16.11.0.dist-info/METADATA
euroeval-16.11.0.dist-info/WHEEL
euroeval-16.11.0.dist-info/entry_points.txt
euroeval-16.11.0.dist-info/licenses/LICENSE
euroeval-16.11.0.dist-info/RECORD
