Metadata-Version: 2.4
Name: EuroEval
Version: 16.11.0
Summary: The robust European language model benchmark.
Project-URL: Repository, https://github.com/EuroEval/EuroEval
Project-URL: Issues, https://github.com/EuroEval/EuroEval/issues
Author-email: Dan Saattrup Smart <dan.smart@alexandra.dk>
Maintainer-email: Dan Saattrup Smart <dan.smart@alexandra.dk>
License: MIT License
License-File: LICENSE
Requires-Python: <4.0,>=3.11
Requires-Dist: accelerate>=1.9.0
Requires-Dist: bert-score>=0.3.13
Requires-Dist: click>=8.1.3
Requires-Dist: cloudpickle>=3.1.1
Requires-Dist: datasets>=3.5.0
Requires-Dist: demjson3>=3.0.6
Requires-Dist: evaluate>=0.4.1
Requires-Dist: huggingface-hub>=0.30.1
Requires-Dist: levenshtein>=0.24.0
Requires-Dist: litellm>=1.75.6
Requires-Dist: mistral-common[soundfile]
Requires-Dist: more-itertools>=10.5.0
Requires-Dist: numpy>=2.0.0
Requires-Dist: ollama>=0.5.1
Requires-Dist: pandas>=2.2.0
Requires-Dist: peft>=0.15.0
Requires-Dist: protobuf>=2.0.0
Requires-Dist: pydantic>=2.6.0
Requires-Dist: pyinfer>=0.0.3
Requires-Dist: python-dotenv>=1.0.1
Requires-Dist: rouge-score>=0.1.2
Requires-Dist: sacrebleu>=2.5.1
Requires-Dist: sacremoses>=0.1.1
Requires-Dist: scikit-learn==1.6.1
Requires-Dist: sentencepiece>=0.1.96
Requires-Dist: seqeval>=1.2.2
Requires-Dist: setuptools>=75.8.2
Requires-Dist: tenacity>=9.0.0
Requires-Dist: termcolor>=2.0.0
Requires-Dist: torch>=2.6.0
Requires-Dist: transformers[mistral-common]>=4.56.0
Provides-Extra: all
Requires-Dist: bitsandbytes>=0.43.1; (platform_system == 'Linux') and extra == 'all'
Requires-Dist: fbgemm-gpu>=1.0.0; (platform_system == 'Linux') and extra == 'all'
Requires-Dist: ray>=2.53.0; (platform_system == 'Linux') and extra == 'all'
Requires-Dist: timm>=1.0.19; extra == 'all'
Requires-Dist: vllm[flashinfer]==0.11.0; (platform_system == 'Linux') and extra == 'all'
Provides-Extra: generative
Requires-Dist: bitsandbytes>=0.43.1; (platform_system == 'Linux') and extra == 'generative'
Requires-Dist: fbgemm-gpu>=1.0.0; (platform_system == 'Linux') and extra == 'generative'
Requires-Dist: ray>=2.53.0; (platform_system == 'Linux') and extra == 'generative'
Requires-Dist: timm>=1.0.19; extra == 'generative'
Requires-Dist: vllm[flashinfer]==0.11.0; (platform_system == 'Linux') and extra == 'generative'
